gdvc_mini.py
gdvc-0.0.2.dist-info/METADATA
gdvc-0.0.2.dist-info/WHEEL
gdvc-0.0.2.dist-info/entry_points.txt
gdvc-0.0.2.dist-info/top_level.txt
gdvc-0.0.2.dist-info/RECORD
